{"nodes": [{"id": "amenity", "label": "amenity.ts", "file_type": "code", "source_file": "homestay-admin\\src\\api\\amenity.ts", "source_location": "L1"}, {"id": "amenity_getallavailableamenities", "label": "getAllAvailableAmenities()", "file_type": "code", "source_file": "homestay-admin\\src\\api\\amenity.ts", "source_location": "L32"}], "edges": [{"source": "amenity", "target": "request", "relation": "imports_from", "confidence": "EXTRACTED", "source_file": "homestay-admin\\src\\api\\amenity.ts", "source_location": "L1", "weight": 1.0}, {"source": "amenity", "target": "amenity_getallavailableamenities", "relation": "contains", "confidence": "EXTRACTED", "source_file": "homestay-admin\\src\\api\\amenity.ts", "source_location": "L32", "weight": 1.0}]}