{"nodes": [{"id": "ordernotificationservice", "label": "OrderNotificationService.java", "file_type": "code", "source_file": "homestay-backend\\src\\main\\java\\com\\homestay3\\homestaybackend\\service\\OrderNotificationService.java", "source_location": "L1"}, {"id": "ordernotificationservice_ordernotificationservice", "label": "OrderNotificationService", "file_type": "code", "source_file": "homestay-backend\\src\\main\\java\\com\\homestay3\\homestaybackend\\service\\OrderNotificationService.java", "source_location": "L10"}, {"id": "ordernotificationservice_ordernotificationservice_sendorderautoconfirmednotification", "label": ".sendOrderAutoConfirmedNotification()", "file_type": "code", "source_file": "homestay-backend\\src\\main\\java\\com\\homestay3\\homestaybackend\\service\\OrderNotificationService.java", "source_location": "L21"}, {"id": "ordernotificationservice_ordernotificationservice_sendorderbookingrequestnotification", "label": ".sendOrderBookingRequestNotification()", "file_type": "code", "source_file": "homestay-backend\\src\\main\\java\\com\\homestay3\\homestaybackend\\service\\OrderNotificationService.java", "source_location": "L32"}, {"id": "ordernotificationservice_ordernotificationservice_sendorderconfirmednotification", "label": ".sendOrderConfirmedNotification()", "file_type": "code", "source_file": "homestay-backend\\src\\main\\java\\com\\homestay3\\homestaybackend\\service\\OrderNotificationService.java", "source_location": "L45"}, {"id": "ordernotificationservice_ordernotificationservice_sendordercompletednotification", "label": ".sendOrderCompletedNotification()", "file_type": "code", "source_file": "homestay-backend\\src\\main\\java\\com\\homestay3\\homestaybackend\\service\\OrderNotificationService.java", "source_location": "L60"}, {"id": "ordernotificationservice_ordernotificationservice_sendorderpaymentsuccessnotification", "label": ".sendOrderPaymentSuccessNotification()", "file_type": "code", "source_file": "homestay-backend\\src\\main\\java\\com\\homestay3\\homestaybackend\\service\\OrderNotificationService.java", "source_location": "L76"}, {"id": "ordernotificationservice_ordernotificationservice_sendorderrejectednotification", "label": ".sendOrderRejectedNotification()", "file_type": "code", "source_file": "homestay-backend\\src\\main\\java\\com\\homestay3\\homestaybackend\\service\\OrderNotificationService.java", "source_location": "L91"}, {"id": "ordernotificationservice_ordernotificationservice_sendordercancellednotification", "label": ".sendOrderCancelledNotification()", "file_type": "code", "source_file": "homestay-backend\\src\\main\\java\\com\\homestay3\\homestaybackend\\service\\OrderNotificationService.java", "source_location": "L106"}, {"id": "ordernotificationservice_ordernotificationservice_sendorderrefundrequestednotification", "label": ".sendOrderRefundRequestedNotification()", "file_type": "code", "source_file": "homestay-backend\\src\\main\\java\\com\\homestay3\\homestaybackend\\service\\OrderNotificationService.java", "source_location": "L120"}, {"id": "ordernotificationservice_ordernotificationservice_sendorderrefundapprovednotification", "label": ".sendOrderRefundApprovedNotification()", "file_type": "code", "source_file": "homestay-backend\\src\\main\\java\\com\\homestay3\\homestaybackend\\service\\OrderNotificationService.java", "source_location": "L131"}, {"id": "ordernotificationservice_ordernotificationservice_sendorderrefundrejectednotification", "label": ".sendOrderRefundRejectedNotification()", "file_type": "code", "source_file": "homestay-backend\\src\\main\\java\\com\\homestay3\\homestaybackend\\service\\OrderNotificationService.java", "source_location": "L141"}, {"id": "ordernotificationservice_ordernotificationservice_sendorderrefundcompletednotification", "label": ".sendOrderRefundCompletedNotification()", "file_type": "code", "source_file": "homestay-backend\\src\\main\\java\\com\\homestay3\\homestaybackend\\service\\OrderNotificationService.java", "source_location": "L151"}, {"id": "ordernotificationservice_ordernotificationservice_sendorderrefundinitiatednotification", "label": ".sendOrderRefundInitiatedNotification()", "file_type": "code", "source_file": "homestay-backend\\src\\main\\java\\com\\homestay3\\homestaybackend\\service\\OrderNotificationService.java", "source_location": "L161"}, {"id": "ordernotificationservice_ordernotificationservice_senddisputeraisednotification", "label": ".sendDisputeRaisedNotification()", "file_type": "code", "source_file": "homestay-backend\\src\\main\\java\\com\\homestay3\\homestaybackend\\service\\OrderNotificationService.java", "source_location": "L173"}, {"id": "ordernotificationservice_ordernotificationservice_senddisputeresolvednotification", "label": ".sendDisputeResolvedNotification()", "file_type": "code", "source_file": "homestay-backend\\src\\main\\java\\com\\homestay3\\homestaybackend\\service\\OrderNotificationService.java", "source_location": "L187"}, {"id": "ordernotificationservice_ordernotificationservice_sendrefundpendingnotification", "label": ".sendRefundPendingNotification()", "file_type": "code", "source_file": "homestay-backend\\src\\main\\java\\com\\homestay3\\homestaybackend\\service\\OrderNotificationService.java", "source_location": "L200"}], "edges": [{"source": "ordernotificationservice", "target": "entitytype", "relation": "imports", "confidence": "EXTRACTED", "source_file": "homestay-backend\\src\\main\\java\\com\\homestay3\\homestaybackend\\service\\OrderNotificationService.java", "source_location": "L3", "weight": 1.0}, {"source": "ordernotificationservice", "target": "notificationtype", "relation": "imports", "confidence": "EXTRACTED", "source_file": "homestay-backend\\src\\main\\java\\com\\homestay3\\homestaybackend\\service\\OrderNotificationService.java", "source_location": "L4", "weight": 1.0}, {"source": "ordernotificationservice", "target": "ordernotificationservice_ordernotificationservice", "relation": "contains", "confidence": "EXTRACTED", "source_file": "homestay-backend\\src\\main\\java\\com\\homestay3\\homestaybackend\\service\\OrderNotificationService.java", "source_location": "L10", "weight": 1.0}, {"source": "ordernotificationservice_ordernotificationservice", "target": "ordernotificationservice_ordernotificationservice_sendorderautoconfirmednotification", "relation": "method", "confidence": "EXTRACTED", "source_file": "homestay-backend\\src\\main\\java\\com\\homestay3\\homestaybackend\\service\\OrderNotificationService.java", "source_location": "L21", "weight": 1.0}, {"source": "ordernotificationservice_ordernotificationservice", "target": "ordernotificationservice_ordernotificationservice_sendorderbookingrequestnotification", "relation": "method", "confidence": "EXTRACTED", "source_file": "homestay-backend\\src\\main\\java\\com\\homestay3\\homestaybackend\\service\\OrderNotificationService.java", "source_location": "L32", "weight": 1.0}, {"source": "ordernotificationservice_ordernotificationservice", "target": "ordernotificationservice_ordernotificationservice_sendorderconfirmednotification", "relation": "method", "confidence": "EXTRACTED", "source_file": "homestay-backend\\src\\main\\java\\com\\homestay3\\homestaybackend\\service\\OrderNotificationService.java", "source_location": "L45", "weight": 1.0}, {"source": "ordernotificationservice_ordernotificationservice", "target": "ordernotificationservice_ordernotificationservice_sendordercompletednotification", "relation": "method", "confidence": "EXTRACTED", "source_file": "homestay-backend\\src\\main\\java\\com\\homestay3\\homestaybackend\\service\\OrderNotificationService.java", "source_location": "L60", "weight": 1.0}, {"source": "ordernotificationservice_ordernotificationservice", "target": "ordernotificationservice_ordernotificationservice_sendorderpaymentsuccessnotification", "relation": "method", "confidence": "EXTRACTED", "source_file": "homestay-backend\\src\\main\\java\\com\\homestay3\\homestaybackend\\service\\OrderNotificationService.java", "source_location": "L76", "weight": 1.0}, {"source": "ordernotificationservice_ordernotificationservice", "target": "ordernotificationservice_ordernotificationservice_sendorderrejectednotification", "relation": "method", "confidence": "EXTRACTED", "source_file": "homestay-backend\\src\\main\\java\\com\\homestay3\\homestaybackend\\service\\OrderNotificationService.java", "source_location": "L91", "weight": 1.0}, {"source": "ordernotificationservice_ordernotificationservice", "target": "ordernotificationservice_ordernotificationservice_sendordercancellednotification", "relation": "method", "confidence": "EXTRACTED", "source_file": "homestay-backend\\src\\main\\java\\com\\homestay3\\homestaybackend\\service\\OrderNotificationService.java", "source_location": "L106", "weight": 1.0}, {"source": "ordernotificationservice_ordernotificationservice", "target": "ordernotificationservice_ordernotificationservice_sendorderrefundrequestednotification", "relation": "method", "confidence": "EXTRACTED", "source_file": "homestay-backend\\src\\main\\java\\com\\homestay3\\homestaybackend\\service\\OrderNotificationService.java", "source_location": "L120", "weight": 1.0}, {"source": "ordernotificationservice_ordernotificationservice", "target": "ordernotificationservice_ordernotificationservice_sendorderrefundapprovednotification", "relation": "method", "confidence": "EXTRACTED", "source_file": "homestay-backend\\src\\main\\java\\com\\homestay3\\homestaybackend\\service\\OrderNotificationService.java", "source_location": "L131", "weight": 1.0}, {"source": "ordernotificationservice_ordernotificationservice", "target": "ordernotificationservice_ordernotificationservice_sendorderrefundrejectednotification", "relation": "method", "confidence": "EXTRACTED", "source_file": "homestay-backend\\src\\main\\java\\com\\homestay3\\homestaybackend\\service\\OrderNotificationService.java", "source_location": "L141", "weight": 1.0}, {"source": "ordernotificationservice_ordernotificationservice", "target": "ordernotificationservice_ordernotificationservice_sendorderrefundcompletednotification", "relation": "method", "confidence": "EXTRACTED", "source_file": "homestay-backend\\src\\main\\java\\com\\homestay3\\homestaybackend\\service\\OrderNotificationService.java", "source_location": "L151", "weight": 1.0}, {"source": "ordernotificationservice_ordernotificationservice", "target": "ordernotificationservice_ordernotificationservice_sendorderrefundinitiatednotification", "relation": "method", "confidence": "EXTRACTED", "source_file": "homestay-backend\\src\\main\\java\\com\\homestay3\\homestaybackend\\service\\OrderNotificationService.java", "source_location": "L161", "weight": 1.0}, {"source": "ordernotificationservice_ordernotificationservice", "target": "ordernotificationservice_ordernotificationservice_senddisputeraisednotification", "relation": "method", "confidence": "EXTRACTED", "source_file": "homestay-backend\\src\\main\\java\\com\\homestay3\\homestaybackend\\service\\OrderNotificationService.java", "source_location": "L173", "weight": 1.0}, {"source": "ordernotificationservice_ordernotificationservice", "target": "ordernotificationservice_ordernotificationservice_senddisputeresolvednotification", "relation": "method", "confidence": "EXTRACTED", "source_file": "homestay-backend\\src\\main\\java\\com\\homestay3\\homestaybackend\\service\\OrderNotificationService.java", "source_location": "L187", "weight": 1.0}, {"source": "ordernotificationservice_ordernotificationservice", "target": "ordernotificationservice_ordernotificationservice_sendrefundpendingnotification", "relation": "method", "confidence": "EXTRACTED", "source_file": "homestay-backend\\src\\main\\java\\com\\homestay3\\homestaybackend\\service\\OrderNotificationService.java", "source_location": "L200", "weight": 1.0}]}