{"nodes": [{"id": "homestaygroupservice", "label": "HomestayGroupService.java", "file_type": "code", "source_file": "homestay-backend\\src\\main\\java\\com\\homestay3\\homestaybackend\\service\\HomestayGroupService.java", "source_location": "L1"}, {"id": "homestaygroupservice_homestaygroupservice", "label": "HomestayGroupService", "file_type": "code", "source_file": "homestay-backend\\src\\main\\java\\com\\homestay3\\homestaybackend\\service\\HomestayGroupService.java", "source_location": "L26"}, {"id": "homestaygroupservice_homestaygroupservice_getgroupsbyowner", "label": ".getGroupsByOwner()", "file_type": "code", "source_file": "homestay-backend\\src\\main\\java\\com\\homestay3\\homestaybackend\\service\\HomestayGroupService.java", "source_location": "L36"}, {"id": "homestaygroupservice_homestaygroupservice_getgroupbyid", "label": ".getGroupById()", "file_type": "code", "source_file": "homestay-backend\\src\\main\\java\\com\\homestay3\\homestaybackend\\service\\HomestayGroupService.java", "source_location": "L47"}, {"id": "homestaygroupservice_homestaygroupservice_creategroup", "label": ".createGroup()", "file_type": "code", "source_file": "homestay-backend\\src\\main\\java\\com\\homestay3\\homestaybackend\\service\\HomestayGroupService.java", "source_location": "L57"}, {"id": "homestaygroupservice_homestaygroupservice_updategroup", "label": ".updateGroup()", "file_type": "code", "source_file": "homestay-backend\\src\\main\\java\\com\\homestay3\\homestaybackend\\service\\HomestayGroupService.java", "source_location": "L90"}, {"id": "homestaygroupservice_homestaygroupservice_deletegroup", "label": ".deleteGroup()", "file_type": "code", "source_file": "homestay-backend\\src\\main\\java\\com\\homestay3\\homestaybackend\\service\\HomestayGroupService.java", "source_location": "L129"}, {"id": "homestaygroupservice_homestaygroupservice_assignhomestaystogroup", "label": ".assignHomestaysToGroup()", "file_type": "code", "source_file": "homestay-backend\\src\\main\\java\\com\\homestay3\\homestaybackend\\service\\HomestayGroupService.java", "source_location": "L151"}, {"id": "homestaygroupservice_homestaygroupservice_removehomestaysfromgroup", "label": ".removeHomestaysFromGroup()", "file_type": "code", "source_file": "homestay-backend\\src\\main\\java\\com\\homestay3\\homestaybackend\\service\\HomestayGroupService.java", "source_location": "L171"}, {"id": "homestaygroupservice_homestaygroupservice_gethomestaysbygroup", "label": ".getHomestaysByGroup()", "file_type": "code", "source_file": "homestay-backend\\src\\main\\java\\com\\homestay3\\homestaybackend\\service\\HomestayGroupService.java", "source_location": "L190"}, {"id": "homestaygroupservice_homestaygroupservice_todto", "label": ".toDTO()", "file_type": "code", "source_file": "homestay-backend\\src\\main\\java\\com\\homestay3\\homestaybackend\\service\\HomestayGroupService.java", "source_location": "L213"}, {"id": "homestaygroupservice_homestaygroupservice_admingetgroups", "label": ".adminGetGroups()", "file_type": "code", "source_file": "homestay-backend\\src\\main\\java\\com\\homestay3\\homestaybackend\\service\\HomestayGroupService.java", "source_location": "L236"}, {"id": "homestaygroupservice_homestaygroupservice_admingetgroupbyid", "label": ".adminGetGroupById()", "file_type": "code", "source_file": "homestay-backend\\src\\main\\java\\com\\homestay3\\homestaybackend\\service\\HomestayGroupService.java", "source_location": "L253"}, {"id": "homestaygroupservice_homestaygroupservice_admintogglegroupenabled", "label": ".adminToggleGroupEnabled()", "file_type": "code", "source_file": "homestay-backend\\src\\main\\java\\com\\homestay3\\homestaybackend\\service\\HomestayGroupService.java", "source_location": "L259"}, {"id": "homestaygroupservice_homestaygroupservice_admindeletegroup", "label": ".adminDeleteGroup()", "file_type": "code", "source_file": "homestay-backend\\src\\main\\java\\com\\homestay3\\homestaybackend\\service\\HomestayGroupService.java", "source_location": "L269"}], "edges": [{"source": "homestaygroupservice", "target": "homestaydto", "relation": "imports", "confidence": "EXTRACTED", "source_file": "homestay-backend\\src\\main\\java\\com\\homestay3\\homestaybackend\\service\\HomestayGroupService.java", "source_location": "L3", "weight": 1.0}, {"source": "homestaygroupservice", "target": "homestaygroupdto", "relation": "imports", "confidence": "EXTRACTED", "source_file": "homestay-backend\\src\\main\\java\\com\\homestay3\\homestaybackend\\service\\HomestayGroupService.java", "source_location": "L4", "weight": 1.0}, {"source": "homestaygroupservice", "target": "homestaygrouprequest", "relation": "imports", "confidence": "EXTRACTED", "source_file": "homestay-backend\\src\\main\\java\\com\\homestay3\\homestaybackend\\service\\HomestayGroupService.java", "source_location": "L5", "weight": 1.0}, {"source": "homestaygroupservice", "target": "homestay", "relation": "imports", "confidence": "EXTRACTED", "source_file": "homestay-backend\\src\\main\\java\\com\\homestay3\\homestaybackend\\service\\HomestayGroupService.java", "source_location": "L6", "weight": 1.0}, {"source": "homestaygroupservice", "target": "homestaygroup", "relation": "imports", "confidence": "EXTRACTED", "source_file": "homestay-backend\\src\\main\\java\\com\\homestay3\\homestaybackend\\service\\HomestayGroupService.java", "source_location": "L7", "weight": 1.0}, {"source": "homestaygroupservice", "target": "user", "relation": "imports", "confidence": "EXTRACTED", "source_file": "homestay-backend\\src\\main\\java\\com\\homestay3\\homestaybackend\\service\\HomestayGroupService.java", "source_location": "L8", "weight": 1.0}, {"source": "homestaygroupservice", "target": "resourcenotfoundexception", "relation": "imports", "confidence": "EXTRACTED", "source_file": "homestay-backend\\src\\main\\java\\com\\homestay3\\homestaybackend\\service\\HomestayGroupService.java", "source_location": "L9", "weight": 1.0}, {"source": "homestaygroupservice", "target": "homestaygrouprepository", "relation": "imports", "confidence": "EXTRACTED", "source_file": "homestay-backend\\src\\main\\java\\com\\homestay3\\homestaybackend\\service\\HomestayGroupService.java", "source_location": "L10", "weight": 1.0}, {"source": "homestaygroupservice", "target": "homestayrepository", "relation": "imports", "confidence": "EXTRACTED", "source_file": "homestay-backend\\src\\main\\java\\com\\homestay3\\homestaybackend\\service\\HomestayGroupService.java", "source_location": "L11", "weight": 1.0}, {"source": "homestaygroupservice", "target": "userrepository", "relation": "imports", "confidence": "EXTRACTED", "source_file": "homestay-backend\\src\\main\\java\\com\\homestay3\\homestaybackend\\service\\HomestayGroupService.java", "source_location": "L12", "weight": 1.0}, {"source": "homestaygroupservice", "target": "requiredargsconstructor", "relation": "imports", "confidence": "EXTRACTED", "source_file": "homestay-backend\\src\\main\\java\\com\\homestay3\\homestaybackend\\service\\HomestayGroupService.java", "source_location": "L13", "weight": 1.0}, {"source": "homestaygroupservice", "target": "slf4j", "relation": "imports", "confidence": "EXTRACTED", "source_file": "homestay-backend\\src\\main\\java\\com\\homestay3\\homestaybackend\\service\\HomestayGroupService.java", "source_location": "L14", "weight": 1.0}, {"source": "homestaygroupservice", "target": "page", "relation": "imports", "confidence": "EXTRACTED", "source_file": "homestay-backend\\src\\main\\java\\com\\homestay3\\homestaybackend\\service\\HomestayGroupService.java", "source_location": "L15", "weight": 1.0}, {"source": "homestaygroupservice", "target": "pagerequest", "relation": "imports", "confidence": "EXTRACTED", "source_file": "homestay-backend\\src\\main\\java\\com\\homestay3\\homestaybackend\\service\\HomestayGroupService.java", "source_location": "L16", "weight": 1.0}, {"source": "homestaygroupservice", "target": "pageable", "relation": "imports", "confidence": "EXTRACTED", "source_file": "homestay-backend\\src\\main\\java\\com\\homestay3\\homestaybackend\\service\\HomestayGroupService.java", "source_location": "L17", "weight": 1.0}, {"source": "homestaygroupservice", "target": "sort", "relation": "imports", "confidence": "EXTRACTED", "source_file": "homestay-backend\\src\\main\\java\\com\\homestay3\\homestaybackend\\service\\HomestayGroupService.java", "source_location": "L18", "weight": 1.0}, {"source": "homestaygroupservice", "target": "service", "relation": "imports", "confidence": "EXTRACTED", "source_file": "homestay-backend\\src\\main\\java\\com\\homestay3\\homestaybackend\\service\\HomestayGroupService.java", "source_location": "L19", "weight": 1.0}, {"source": "homestaygroupservice", "target": "transactional", "relation": "imports", "confidence": "EXTRACTED", "source_file": "homestay-backend\\src\\main\\java\\com\\homestay3\\homestaybackend\\service\\HomestayGroupService.java", "source_location": "L20", "weight": 1.0}, {"source": "homestaygroupservice", "target": "datetimeformatter", "relation": "imports", "confidence": "EXTRACTED", "source_file": "homestay-backend\\src\\main\\java\\com\\homestay3\\homestaybackend\\service\\HomestayGroupService.java", "source_location": "L22", "weight": 1.0}, {"source": "homestaygroupservice", "target": "list", "relation": "imports", "confidence": "EXTRACTED", "source_file": "homestay-backend\\src\\main\\java\\com\\homestay3\\homestaybackend\\service\\HomestayGroupService.java", "source_location": "L23", "weight": 1.0}, {"source": "homestaygroupservice", "target": "collectors", "relation": "imports", "confidence": "EXTRACTED", "source_file": "homestay-backend\\src\\main\\java\\com\\homestay3\\homestaybackend\\service\\HomestayGroupService.java", "source_location": "L24", "weight": 1.0}, {"source": "homestaygroupservice", "target": "homestaygroupservice_homestaygroupservice", "relation": "contains", "confidence": "EXTRACTED", "source_file": "homestay-backend\\src\\main\\java\\com\\homestay3\\homestaybackend\\service\\HomestayGroupService.java", "source_location": "L26", "weight": 1.0}, {"source": "homestaygroupservice_homestaygroupservice", "target": "homestaygroupservice_homestaygroupservice_getgroupsbyowner", "relation": "method", "confidence": "EXTRACTED", "source_file": "homestay-backend\\src\\main\\java\\com\\homestay3\\homestaybackend\\service\\HomestayGroupService.java", "source_location": "L36", "weight": 1.0}, {"source": "homestaygroupservice_homestaygroupservice", "target": "homestaygroupservice_homestaygroupservice_getgroupbyid", "relation": "method", "confidence": "EXTRACTED", "source_file": "homestay-backend\\src\\main\\java\\com\\homestay3\\homestaybackend\\service\\HomestayGroupService.java", "source_location": "L47", "weight": 1.0}, {"source": "homestaygroupservice_homestaygroupservice", "target": "homestaygroupservice_homestaygroupservice_creategroup", "relation": "method", "confidence": "EXTRACTED", "source_file": "homestay-backend\\src\\main\\java\\com\\homestay3\\homestaybackend\\service\\HomestayGroupService.java", "source_location": "L57", "weight": 1.0}, {"source": "homestaygroupservice_homestaygroupservice", "target": "homestaygroupservice_homestaygroupservice_updategroup", "relation": "method", "confidence": "EXTRACTED", "source_file": "homestay-backend\\src\\main\\java\\com\\homestay3\\homestaybackend\\service\\HomestayGroupService.java", "source_location": "L90", "weight": 1.0}, {"source": "homestaygroupservice_homestaygroupservice", "target": "homestaygroupservice_homestaygroupservice_deletegroup", "relation": "method", "confidence": "EXTRACTED", "source_file": "homestay-backend\\src\\main\\java\\com\\homestay3\\homestaybackend\\service\\HomestayGroupService.java", "source_location": "L129", "weight": 1.0}, {"source": "homestaygroupservice_homestaygroupservice", "target": "homestaygroupservice_homestaygroupservice_assignhomestaystogroup", "relation": "method", "confidence": "EXTRACTED", "source_file": "homestay-backend\\src\\main\\java\\com\\homestay3\\homestaybackend\\service\\HomestayGroupService.java", "source_location": "L151", "weight": 1.0}, {"source": "homestaygroupservice_homestaygroupservice", "target": "homestaygroupservice_homestaygroupservice_removehomestaysfromgroup", "relation": "method", "confidence": "EXTRACTED", "source_file": "homestay-backend\\src\\main\\java\\com\\homestay3\\homestaybackend\\service\\HomestayGroupService.java", "source_location": "L171", "weight": 1.0}, {"source": "homestaygroupservice_homestaygroupservice", "target": "homestaygroupservice_homestaygroupservice_gethomestaysbygroup", "relation": "method", "confidence": "EXTRACTED", "source_file": "homestay-backend\\src\\main\\java\\com\\homestay3\\homestaybackend\\service\\HomestayGroupService.java", "source_location": "L190", "weight": 1.0}, {"source": "homestaygroupservice_homestaygroupservice", "target": "homestaygroupservice_homestaygroupservice_todto", "relation": "method", "confidence": "EXTRACTED", "source_file": "homestay-backend\\src\\main\\java\\com\\homestay3\\homestaybackend\\service\\HomestayGroupService.java", "source_location": "L213", "weight": 1.0}, {"source": "homestaygroupservice_homestaygroupservice", "target": "homestaygroupservice_homestaygroupservice_admingetgroups", "relation": "method", "confidence": "EXTRACTED", "source_file": "homestay-backend\\src\\main\\java\\com\\homestay3\\homestaybackend\\service\\HomestayGroupService.java", "source_location": "L236", "weight": 1.0}, {"source": "homestaygroupservice_homestaygroupservice", "target": "homestaygroupservice_homestaygroupservice_admingetgroupbyid", "relation": "method", "confidence": "EXTRACTED", "source_file": "homestay-backend\\src\\main\\java\\com\\homestay3\\homestaybackend\\service\\HomestayGroupService.java", "source_location": "L253", "weight": 1.0}, {"source": "homestaygroupservice_homestaygroupservice", "target": "homestaygroupservice_homestaygroupservice_admintogglegroupenabled", "relation": "method", "confidence": "EXTRACTED", "source_file": "homestay-backend\\src\\main\\java\\com\\homestay3\\homestaybackend\\service\\HomestayGroupService.java", "source_location": "L259", "weight": 1.0}, {"source": "homestaygroupservice_homestaygroupservice", "target": "homestaygroupservice_homestaygroupservice_admindeletegroup", "relation": "method", "confidence": "EXTRACTED", "source_file": "homestay-backend\\src\\main\\java\\com\\homestay3\\homestaybackend\\service\\HomestayGroupService.java", "source_location": "L269", "weight": 1.0}, {"source": "homestaygroupservice_homestaygroupservice_getgroupbyid", "target": "homestaygroupservice_homestaygroupservice_todto", "relation": "calls", "confidence": "INFERRED", "source_file": "homestay-backend\\src\\main\\java\\com\\homestay3\\homestaybackend\\service\\HomestayGroupService.java", "source_location": "L54", "weight": 0.8}, {"source": "homestaygroupservice_homestaygroupservice_creategroup", "target": "homestaygroupservice_homestaygroupservice_todto", "relation": "calls", "confidence": "INFERRED", "source_file": "homestay-backend\\src\\main\\java\\com\\homestay3\\homestaybackend\\service\\HomestayGroupService.java", "source_location": "L87", "weight": 0.8}, {"source": "homestaygroupservice_homestaygroupservice_updategroup", "target": "homestaygroupservice_homestaygroupservice_todto", "relation": "calls", "confidence": "INFERRED", "source_file": "homestay-backend\\src\\main\\java\\com\\homestay3\\homestaybackend\\service\\HomestayGroupService.java", "source_location": "L126", "weight": 0.8}, {"source": "homestaygroupservice_homestaygroupservice_admingetgroupbyid", "target": "homestaygroupservice_homestaygroupservice_todto", "relation": "calls", "confidence": "INFERRED", "source_file": "homestay-backend\\src\\main\\java\\com\\homestay3\\homestaybackend\\service\\HomestayGroupService.java", "source_location": "L256", "weight": 0.8}, {"source": "homestaygroupservice_homestaygroupservice_admintogglegroupenabled", "target": "homestaygroupservice_homestaygroupservice_todto", "relation": "calls", "confidence": "INFERRED", "source_file": "homestay-backend\\src\\main\\java\\com\\homestay3\\homestaybackend\\service\\HomestayGroupService.java", "source_location": "L266", "weight": 0.8}]}