{"nodes": [{"id": "userfavorite", "label": "UserFavorite.java", "file_type": "code", "source_file": "homestay-backend\\src\\main\\java\\com\\homestay3\\homestaybackend\\entity\\UserFavorite.java", "source_location": "L1"}, {"id": "userfavorite_userfavorite", "label": "UserFavorite", "file_type": "code", "source_file": "homestay-backend\\src\\main\\java\\com\\homestay3\\homestaybackend\\entity\\UserFavorite.java", "source_location": "L6"}, {"id": "userfavorite_userfavorite_userfavorite", "label": ".UserFavorite()", "file_type": "code", "source_file": "homestay-backend\\src\\main\\java\\com\\homestay3\\homestaybackend\\entity\\UserFavorite.java", "source_location": "L33"}, {"id": "userfavorite_userfavorite_getid", "label": ".getId()", "file_type": "code", "source_file": "homestay-backend\\src\\main\\java\\com\\homestay3\\homestaybackend\\entity\\UserFavorite.java", "source_location": "L43"}, {"id": "userfavorite_userfavorite_setid", "label": ".setId()", "file_type": "code", "source_file": "homestay-backend\\src\\main\\java\\com\\homestay3\\homestaybackend\\entity\\UserFavorite.java", "source_location": "L47"}, {"id": "userfavorite_userfavorite_getuserid", "label": ".getUserId()", "file_type": "code", "source_file": "homestay-backend\\src\\main\\java\\com\\homestay3\\homestaybackend\\entity\\UserFavorite.java", "source_location": "L51"}, {"id": "userfavorite_userfavorite_setuserid", "label": ".setUserId()", "file_type": "code", "source_file": "homestay-backend\\src\\main\\java\\com\\homestay3\\homestaybackend\\entity\\UserFavorite.java", "source_location": "L55"}, {"id": "userfavorite_userfavorite_gethomestayid", "label": ".getHomestayId()", "file_type": "code", "source_file": "homestay-backend\\src\\main\\java\\com\\homestay3\\homestaybackend\\entity\\UserFavorite.java", "source_location": "L59"}, {"id": "userfavorite_userfavorite_sethomestayid", "label": ".setHomestayId()", "file_type": "code", "source_file": "homestay-backend\\src\\main\\java\\com\\homestay3\\homestaybackend\\entity\\UserFavorite.java", "source_location": "L63"}, {"id": "userfavorite_userfavorite_getcreatedat", "label": ".getCreatedAt()", "file_type": "code", "source_file": "homestay-backend\\src\\main\\java\\com\\homestay3\\homestaybackend\\entity\\UserFavorite.java", "source_location": "L67"}, {"id": "userfavorite_userfavorite_setcreatedat", "label": ".setCreatedAt()", "file_type": "code", "source_file": "homestay-backend\\src\\main\\java\\com\\homestay3\\homestaybackend\\entity\\UserFavorite.java", "source_location": "L71"}, {"id": "userfavorite_userfavorite_getuser", "label": ".getUser()", "file_type": "code", "source_file": "homestay-backend\\src\\main\\java\\com\\homestay3\\homestaybackend\\entity\\UserFavorite.java", "source_location": "L75"}, {"id": "userfavorite_userfavorite_setuser", "label": ".setUser()", "file_type": "code", "source_file": "homestay-backend\\src\\main\\java\\com\\homestay3\\homestaybackend\\entity\\UserFavorite.java", "source_location": "L79"}, {"id": "userfavorite_userfavorite_gethomestay", "label": ".getHomestay()", "file_type": "code", "source_file": "homestay-backend\\src\\main\\java\\com\\homestay3\\homestaybackend\\entity\\UserFavorite.java", "source_location": "L83"}, {"id": "userfavorite_userfavorite_sethomestay", "label": ".setHomestay()", "file_type": "code", "source_file": "homestay-backend\\src\\main\\java\\com\\homestay3\\homestaybackend\\entity\\UserFavorite.java", "source_location": "L87"}, {"id": "userfavorite_userfavorite_prepersist", "label": ".prePersist()", "file_type": "code", "source_file": "homestay-backend\\src\\main\\java\\com\\homestay3\\homestaybackend\\entity\\UserFavorite.java", "source_location": "L91"}], "edges": [{"source": "userfavorite", "target": "persistence", "relation": "imports", "confidence": "EXTRACTED", "source_file": "homestay-backend\\src\\main\\java\\com\\homestay3\\homestaybackend\\entity\\UserFavorite.java", "source_location": "L3", "weight": 1.0}, {"source": "userfavorite", "target": "localdatetime", "relation": "imports", "confidence": "EXTRACTED", "source_file": "homestay-backend\\src\\main\\java\\com\\homestay3\\homestaybackend\\entity\\UserFavorite.java", "source_location": "L4", "weight": 1.0}, {"source": "userfavorite", "target": "userfavorite_userfavorite", "relation": "contains", "confidence": "EXTRACTED", "source_file": "homestay-backend\\src\\main\\java\\com\\homestay3\\homestaybackend\\entity\\UserFavorite.java", "source_location": "L6", "weight": 1.0}, {"source": "userfavorite_userfavorite", "target": "userfavorite_userfavorite_userfavorite", "relation": "method", "confidence": "EXTRACTED", "source_file": "homestay-backend\\src\\main\\java\\com\\homestay3\\homestaybackend\\entity\\UserFavorite.java", "source_location": "L33", "weight": 1.0}, {"source": "userfavorite_userfavorite", "target": "userfavorite_userfavorite_userfavorite", "relation": "method", "confidence": "EXTRACTED", "source_file": "homestay-backend\\src\\main\\java\\com\\homestay3\\homestaybackend\\entity\\UserFavorite.java", "source_location": "L36", "weight": 1.0}, {"source": "userfavorite_userfavorite", "target": "userfavorite_userfavorite_getid", "relation": "method", "confidence": "EXTRACTED", "source_file": "homestay-backend\\src\\main\\java\\com\\homestay3\\homestaybackend\\entity\\UserFavorite.java", "source_location": "L43", "weight": 1.0}, {"source": "userfavorite_userfavorite", "target": "userfavorite_userfavorite_setid", "relation": "method", "confidence": "EXTRACTED", "source_file": "homestay-backend\\src\\main\\java\\com\\homestay3\\homestaybackend\\entity\\UserFavorite.java", "source_location": "L47", "weight": 1.0}, {"source": "userfavorite_userfavorite", "target": "userfavorite_userfavorite_getuserid", "relation": "method", "confidence": "EXTRACTED", "source_file": "homestay-backend\\src\\main\\java\\com\\homestay3\\homestaybackend\\entity\\UserFavorite.java", "source_location": "L51", "weight": 1.0}, {"source": "userfavorite_userfavorite", "target": "userfavorite_userfavorite_setuserid", "relation": "method", "confidence": "EXTRACTED", "source_file": "homestay-backend\\src\\main\\java\\com\\homestay3\\homestaybackend\\entity\\UserFavorite.java", "source_location": "L55", "weight": 1.0}, {"source": "userfavorite_userfavorite", "target": "userfavorite_userfavorite_gethomestayid", "relation": "method", "confidence": "EXTRACTED", "source_file": "homestay-backend\\src\\main\\java\\com\\homestay3\\homestaybackend\\entity\\UserFavorite.java", "source_location": "L59", "weight": 1.0}, {"source": "userfavorite_userfavorite", "target": "userfavorite_userfavorite_sethomestayid", "relation": "method", "confidence": "EXTRACTED", "source_file": "homestay-backend\\src\\main\\java\\com\\homestay3\\homestaybackend\\entity\\UserFavorite.java", "source_location": "L63", "weight": 1.0}, {"source": "userfavorite_userfavorite", "target": "userfavorite_userfavorite_getcreatedat", "relation": "method", "confidence": "EXTRACTED", "source_file": "homestay-backend\\src\\main\\java\\com\\homestay3\\homestaybackend\\entity\\UserFavorite.java", "source_location": "L67", "weight": 1.0}, {"source": "userfavorite_userfavorite", "target": "userfavorite_userfavorite_setcreatedat", "relation": "method", "confidence": "EXTRACTED", "source_file": "homestay-backend\\src\\main\\java\\com\\homestay3\\homestaybackend\\entity\\UserFavorite.java", "source_location": "L71", "weight": 1.0}, {"source": "userfavorite_userfavorite", "target": "userfavorite_userfavorite_getuser", "relation": "method", "confidence": "EXTRACTED", "source_file": "homestay-backend\\src\\main\\java\\com\\homestay3\\homestaybackend\\entity\\UserFavorite.java", "source_location": "L75", "weight": 1.0}, {"source": "userfavorite_userfavorite", "target": "userfavorite_userfavorite_setuser", "relation": "method", "confidence": "EXTRACTED", "source_file": "homestay-backend\\src\\main\\java\\com\\homestay3\\homestaybackend\\entity\\UserFavorite.java", "source_location": "L79", "weight": 1.0}, {"source": "userfavorite_userfavorite", "target": "userfavorite_userfavorite_gethomestay", "relation": "method", "confidence": "EXTRACTED", "source_file": "homestay-backend\\src\\main\\java\\com\\homestay3\\homestaybackend\\entity\\UserFavorite.java", "source_location": "L83", "weight": 1.0}, {"source": "userfavorite_userfavorite", "target": "userfavorite_userfavorite_sethomestay", "relation": "method", "confidence": "EXTRACTED", "source_file": "homestay-backend\\src\\main\\java\\com\\homestay3\\homestaybackend\\entity\\UserFavorite.java", "source_location": "L87", "weight": 1.0}, {"source": "userfavorite_userfavorite", "target": "userfavorite_userfavorite_prepersist", "relation": "method", "confidence": "EXTRACTED", "source_file": "homestay-backend\\src\\main\\java\\com\\homestay3\\homestaybackend\\entity\\UserFavorite.java", "source_location": "L91", "weight": 1.0}]}