{"nodes": [{"id": "checkinserviceimpl", "label": "CheckInServiceImpl.java", "file_type": "code", "source_file": "homestay-backend\\src\\main\\java\\com\\homestay3\\homestaybackend\\service\\impl\\CheckInServiceImpl.java", "source_location": "L1"}, {"id": "checkinserviceimpl_checkinserviceimpl", "label": "CheckInServiceImpl", "file_type": "code", "source_file": "homestay-backend\\src\\main\\java\\com\\homestay3\\homestaybackend\\service\\impl\\CheckInServiceImpl.java", "source_location": "L40"}, {"id": "checkinserviceimpl_checkinserviceimpl_preparecheckin", "label": ".prepareCheckIn()", "file_type": "code", "source_file": "homestay-backend\\src\\main\\java\\com\\homestay3\\homestaybackend\\service\\impl\\CheckInServiceImpl.java", "source_location": "L54"}, {"id": "checkinserviceimpl_checkinserviceimpl_getcheckincredential", "label": ".getCheckInCredential()", "file_type": "code", "source_file": "homestay-backend\\src\\main\\java\\com\\homestay3\\homestaybackend\\service\\impl\\CheckInServiceImpl.java", "source_location": "L111"}, {"id": "checkinserviceimpl_checkinserviceimpl_performcheckin", "label": ".performCheckIn()", "file_type": "code", "source_file": "homestay-backend\\src\\main\\java\\com\\homestay3\\homestaybackend\\service\\impl\\CheckInServiceImpl.java", "source_location": "L131"}, {"id": "checkinserviceimpl_checkinserviceimpl_selfcheckin", "label": ".selfCheckIn()", "file_type": "code", "source_file": "homestay-backend\\src\\main\\java\\com\\homestay3\\homestaybackend\\service\\impl\\CheckInServiceImpl.java", "source_location": "L173"}, {"id": "checkinserviceimpl_checkinserviceimpl_confirmarrival", "label": ".confirmArrival()", "file_type": "code", "source_file": "homestay-backend\\src\\main\\java\\com\\homestay3\\homestaybackend\\service\\impl\\CheckInServiceImpl.java", "source_location": "L218"}, {"id": "checkinserviceimpl_checkinserviceimpl_cancelpreparation", "label": ".cancelPreparation()", "file_type": "code", "source_file": "homestay-backend\\src\\main\\java\\com\\homestay3\\homestaybackend\\service\\impl\\CheckInServiceImpl.java", "source_location": "L249"}, {"id": "checkinserviceimpl_checkinserviceimpl_getcheckinrecord", "label": ".getCheckInRecord()", "file_type": "code", "source_file": "homestay-backend\\src\\main\\java\\com\\homestay3\\homestaybackend\\service\\impl\\CheckInServiceImpl.java", "source_location": "L282"}, {"id": "checkinserviceimpl_checkinserviceimpl_validatecheckincode", "label": ".validateCheckInCode()", "file_type": "code", "source_file": "homestay-backend\\src\\main\\java\\com\\homestay3\\homestaybackend\\service\\impl\\CheckInServiceImpl.java", "source_location": "L293"}, {"id": "checkinserviceimpl_checkinserviceimpl_validateaccess", "label": ".validateAccess()", "file_type": "code", "source_file": "homestay-backend\\src\\main\\java\\com\\homestay3\\homestaybackend\\service\\impl\\CheckInServiceImpl.java", "source_location": "L303"}, {"id": "checkinserviceimpl_checkinserviceimpl_getcurrentuser", "label": ".getCurrentUser()", "file_type": "code", "source_file": "homestay-backend\\src\\main\\java\\com\\homestay3\\homestaybackend\\service\\impl\\CheckInServiceImpl.java", "source_location": "L316"}, {"id": "checkinserviceimpl_checkinserviceimpl_isorderowner", "label": ".isOrderOwner()", "file_type": "code", "source_file": "homestay-backend\\src\\main\\java\\com\\homestay3\\homestaybackend\\service\\impl\\CheckInServiceImpl.java", "source_location": "L323"}, {"id": "checkinserviceimpl_checkinserviceimpl_isorderguest", "label": ".isOrderGuest()", "file_type": "code", "source_file": "homestay-backend\\src\\main\\java\\com\\homestay3\\homestaybackend\\service\\impl\\CheckInServiceImpl.java", "source_location": "L328"}, {"id": "checkinserviceimpl_checkinserviceimpl_hasadminauthority", "label": ".hasAdminAuthority()", "file_type": "code", "source_file": "homestay-backend\\src\\main\\java\\com\\homestay3\\homestaybackend\\service\\impl\\CheckInServiceImpl.java", "source_location": "L332"}, {"id": "checkinserviceimpl_checkinserviceimpl_isorderaccessible", "label": ".isOrderAccessible()", "file_type": "code", "source_file": "homestay-backend\\src\\main\\java\\com\\homestay3\\homestaybackend\\service\\impl\\CheckInServiceImpl.java", "source_location": "L336"}, {"id": "checkinserviceimpl_checkinserviceimpl_generatecheckincode", "label": ".generateCheckInCode()", "file_type": "code", "source_file": "homestay-backend\\src\\main\\java\\com\\homestay3\\homestaybackend\\service\\impl\\CheckInServiceImpl.java", "source_location": "L340"}, {"id": "checkinserviceimpl_checkinserviceimpl_parseautocheckintime", "label": ".parseAutoCheckinTime()", "file_type": "code", "source_file": "homestay-backend\\src\\main\\java\\com\\homestay3\\homestaybackend\\service\\impl\\CheckInServiceImpl.java", "source_location": "L345"}, {"id": "checkinserviceimpl_checkinserviceimpl_converttodto", "label": ".convertToDTO()", "file_type": "code", "source_file": "homestay-backend\\src\\main\\java\\com\\homestay3\\homestaybackend\\service\\impl\\CheckInServiceImpl.java", "source_location": "L353"}, {"id": "checkinserviceimpl_checkinserviceimpl_sendcheckincredentialnotification", "label": ".sendCheckInCredentialNotification()", "file_type": "code", "source_file": "homestay-backend\\src\\main\\java\\com\\homestay3\\homestaybackend\\service\\impl\\CheckInServiceImpl.java", "source_location": "L373"}, {"id": "checkinserviceimpl_checkinserviceimpl_sendcheckinconfirmationnotification", "label": ".sendCheckInConfirmationNotification()", "file_type": "code", "source_file": "homestay-backend\\src\\main\\java\\com\\homestay3\\homestaybackend\\service\\impl\\CheckInServiceImpl.java", "source_location": "L395"}], "edges": [{"source": "checkinserviceimpl", "target": "checkincredentialdto", "relation": "imports", "confidence": "EXTRACTED", "source_file": "homestay-backend\\src\\main\\java\\com\\homestay3\\homestaybackend\\service\\impl\\CheckInServiceImpl.java", "source_location": "L3", "weight": 1.0}, {"source": "checkinserviceimpl", "target": "checkindto", "relation": "imports", "confidence": "EXTRACTED", "source_file": "homestay-backend\\src\\main\\java\\com\\homestay3\\homestaybackend\\service\\impl\\CheckInServiceImpl.java", "source_location": "L4", "weight": 1.0}, {"source": "checkinserviceimpl", "target": "checkinrecord", "relation": "imports", "confidence": "EXTRACTED", "source_file": "homestay-backend\\src\\main\\java\\com\\homestay3\\homestaybackend\\service\\impl\\CheckInServiceImpl.java", "source_location": "L5", "weight": 1.0}, {"source": "checkinserviceimpl", "target": "order", "relation": "imports", "confidence": "EXTRACTED", "source_file": "homestay-backend\\src\\main\\java\\com\\homestay3\\homestaybackend\\service\\impl\\CheckInServiceImpl.java", "source_location": "L6", "weight": 1.0}, {"source": "checkinserviceimpl", "target": "user", "relation": "imports", "confidence": "EXTRACTED", "source_file": "homestay-backend\\src\\main\\java\\com\\homestay3\\homestaybackend\\service\\impl\\CheckInServiceImpl.java", "source_location": "L7", "weight": 1.0}, {"source": "checkinserviceimpl", "target": "accessdeniedexception", "relation": "imports", "confidence": "EXTRACTED", "source_file": "homestay-backend\\src\\main\\java\\com\\homestay3\\homestaybackend\\service\\impl\\CheckInServiceImpl.java", "source_location": "L8", "weight": 1.0}, {"source": "checkinserviceimpl", "target": "resourcenotfoundexception", "relation": "imports", "confidence": "EXTRACTED", "source_file": "homestay-backend\\src\\main\\java\\com\\homestay3\\homestaybackend\\service\\impl\\CheckInServiceImpl.java", "source_location": "L9", "weight": 1.0}, {"source": "checkinserviceimpl", "target": "orderstatus", "relation": "imports", "confidence": "EXTRACTED", "source_file": "homestay-backend\\src\\main\\java\\com\\homestay3\\homestaybackend\\service\\impl\\CheckInServiceImpl.java", "source_location": "L10", "weight": 1.0}, {"source": "checkinserviceimpl", "target": "entitytype", "relation": "imports", "confidence": "EXTRACTED", "source_file": "homestay-backend\\src\\main\\java\\com\\homestay3\\homestaybackend\\service\\impl\\CheckInServiceImpl.java", "source_location": "L11", "weight": 1.0}, {"source": "checkinserviceimpl", "target": "notificationtype", "relation": "imports", "confidence": "EXTRACTED", "source_file": "homestay-backend\\src\\main\\java\\com\\homestay3\\homestaybackend\\service\\impl\\CheckInServiceImpl.java", "source_location": "L12", "weight": 1.0}, {"source": "checkinserviceimpl", "target": "checkinrecordrepository", "relation": "imports", "confidence": "EXTRACTED", "source_file": "homestay-backend\\src\\main\\java\\com\\homestay3\\homestaybackend\\service\\impl\\CheckInServiceImpl.java", "source_location": "L13", "weight": 1.0}, {"source": "checkinserviceimpl", "target": "orderrepository", "relation": "imports", "confidence": "EXTRACTED", "source_file": "homestay-backend\\src\\main\\java\\com\\homestay3\\homestaybackend\\service\\impl\\CheckInServiceImpl.java", "source_location": "L14", "weight": 1.0}, {"source": "checkinserviceimpl", "target": "userrepository", "relation": "imports", "confidence": "EXTRACTED", "source_file": "homestay-backend\\src\\main\\java\\com\\homestay3\\homestaybackend\\service\\impl\\CheckInServiceImpl.java", "source_location": "L15", "weight": 1.0}, {"source": "checkinserviceimpl", "target": "checkinservice", "relation": "imports", "confidence": "EXTRACTED", "source_file": "homestay-backend\\src\\main\\java\\com\\homestay3\\homestaybackend\\service\\impl\\CheckInServiceImpl.java", "source_location": "L16", "weight": 1.0}, {"source": "checkinserviceimpl", "target": "notificationservice", "relation": "imports", "confidence": "EXTRACTED", "source_file": "homestay-backend\\src\\main\\java\\com\\homestay3\\homestaybackend\\service\\impl\\CheckInServiceImpl.java", "source_location": "L17", "weight": 1.0}, {"source": "checkinserviceimpl", "target": "systemconfigservice", "relation": "imports", "confidence": "EXTRACTED", "source_file": "homestay-backend\\src\\main\\java\\com\\homestay3\\homestaybackend\\service\\impl\\CheckInServiceImpl.java", "source_location": "L18", "weight": 1.0}, {"source": "checkinserviceimpl", "target": "requiredargsconstructor", "relation": "imports", "confidence": "EXTRACTED", "source_file": "homestay-backend\\src\\main\\java\\com\\homestay3\\homestaybackend\\service\\impl\\CheckInServiceImpl.java", "source_location": "L19", "weight": 1.0}, {"source": "checkinserviceimpl", "target": "logger", "relation": "imports", "confidence": "EXTRACTED", "source_file": "homestay-backend\\src\\main\\java\\com\\homestay3\\homestaybackend\\service\\impl\\CheckInServiceImpl.java", "source_location": "L20", "weight": 1.0}, {"source": "checkinserviceimpl", "target": "loggerfactory", "relation": "imports", "confidence": "EXTRACTED", "source_file": "homestay-backend\\src\\main\\java\\com\\homestay3\\homestaybackend\\service\\impl\\CheckInServiceImpl.java", "source_location": "L21", "weight": 1.0}, {"source": "checkinserviceimpl", "target": "authentication", "relation": "imports", "confidence": "EXTRACTED", "source_file": "homestay-backend\\src\\main\\java\\com\\homestay3\\homestaybackend\\service\\impl\\CheckInServiceImpl.java", "source_location": "L22", "weight": 1.0}, {"source": "checkinserviceimpl", "target": "securitycontextholder", "relation": "imports", "confidence": "EXTRACTED", "source_file": "homestay-backend\\src\\main\\java\\com\\homestay3\\homestaybackend\\service\\impl\\CheckInServiceImpl.java", "source_location": "L23", "weight": 1.0}, {"source": "checkinserviceimpl", "target": "usernamenotfoundexception", "relation": "imports", "confidence": "EXTRACTED", "source_file": "homestay-backend\\src\\main\\java\\com\\homestay3\\homestaybackend\\service\\impl\\CheckInServiceImpl.java", "source_location": "L24", "weight": 1.0}, {"source": "checkinserviceimpl", "target": "service", "relation": "imports", "confidence": "EXTRACTED", "source_file": "homestay-backend\\src\\main\\java\\com\\homestay3\\homestaybackend\\service\\impl\\CheckInServiceImpl.java", "source_location": "L25", "weight": 1.0}, {"source": "checkinserviceimpl", "target": "localtime", "relation": "imports", "confidence": "EXTRACTED", "source_file": "homestay-backend\\src\\main\\java\\com\\homestay3\\homestaybackend\\service\\impl\\CheckInServiceImpl.java", "source_location": "L27", "weight": 1.0}, {"source": "checkinserviceimpl", "target": "datetimeformatter", "relation": "imports", "confidence": "EXTRACTED", "source_file": "homestay-backend\\src\\main\\java\\com\\homestay3\\homestaybackend\\service\\impl\\CheckInServiceImpl.java", "source_location": "L28", "weight": 1.0}, {"source": "checkinserviceimpl", "target": "transactional", "relation": "imports", "confidence": "EXTRACTED", "source_file": "homestay-backend\\src\\main\\java\\com\\homestay3\\homestaybackend\\service\\impl\\CheckInServiceImpl.java", "source_location": "L29", "weight": 1.0}, {"source": "checkinserviceimpl", "target": "localdatetime", "relation": "imports", "confidence": "EXTRACTED", "source_file": "homestay-backend\\src\\main\\java\\com\\homestay3\\homestaybackend\\service\\impl\\CheckInServiceImpl.java", "source_location": "L31", "weight": 1.0}, {"source": "checkinserviceimpl", "target": "localtime", "relation": "imports", "confidence": "EXTRACTED", "source_file": "homestay-backend\\src\\main\\java\\com\\homestay3\\homestaybackend\\service\\impl\\CheckInServiceImpl.java", "source_location": "L32", "weight": 1.0}, {"source": "checkinserviceimpl", "target": "datetimeformatter", "relation": "imports", "confidence": "EXTRACTED", "source_file": "homestay-backend\\src\\main\\java\\com\\homestay3\\homestaybackend\\service\\impl\\CheckInServiceImpl.java", "source_location": "L33", "weight": 1.0}, {"source": "checkinserviceimpl", "target": "optional", "relation": "imports", "confidence": "EXTRACTED", "source_file": "homestay-backend\\src\\main\\java\\com\\homestay3\\homestaybackend\\service\\impl\\CheckInServiceImpl.java", "source_location": "L34", "weight": 1.0}, {"source": "checkinserviceimpl", "target": "random", "relation": "imports", "confidence": "EXTRACTED", "source_file": "homestay-backend\\src\\main\\java\\com\\homestay3\\homestaybackend\\service\\impl\\CheckInServiceImpl.java", "source_location": "L35", "weight": 1.0}, {"source": "checkinserviceimpl", "target": "checkinserviceimpl_checkinserviceimpl", "relation": "contains", "confidence": "EXTRACTED", "source_file": "homestay-backend\\src\\main\\java\\com\\homestay3\\homestaybackend\\service\\impl\\CheckInServiceImpl.java", "source_location": "L40", "weight": 1.0}, {"source": "checkinserviceimpl_checkinserviceimpl", "target": "checkinserviceimpl_checkinserviceimpl_preparecheckin", "relation": "method", "confidence": "EXTRACTED", "source_file": "homestay-backend\\src\\main\\java\\com\\homestay3\\homestaybackend\\service\\impl\\CheckInServiceImpl.java", "source_location": "L54", "weight": 1.0}, {"source": "checkinserviceimpl_checkinserviceimpl", "target": "checkinserviceimpl_checkinserviceimpl_getcheckincredential", "relation": "method", "confidence": "EXTRACTED", "source_file": "homestay-backend\\src\\main\\java\\com\\homestay3\\homestaybackend\\service\\impl\\CheckInServiceImpl.java", "source_location": "L111", "weight": 1.0}, {"source": "checkinserviceimpl_checkinserviceimpl", "target": "checkinserviceimpl_checkinserviceimpl_performcheckin", "relation": "method", "confidence": "EXTRACTED", "source_file": "homestay-backend\\src\\main\\java\\com\\homestay3\\homestaybackend\\service\\impl\\CheckInServiceImpl.java", "source_location": "L131", "weight": 1.0}, {"source": "checkinserviceimpl_checkinserviceimpl", "target": "checkinserviceimpl_checkinserviceimpl_selfcheckin", "relation": "method", "confidence": "EXTRACTED", "source_file": "homestay-backend\\src\\main\\java\\com\\homestay3\\homestaybackend\\service\\impl\\CheckInServiceImpl.java", "source_location": "L173", "weight": 1.0}, {"source": "checkinserviceimpl_checkinserviceimpl", "target": "checkinserviceimpl_checkinserviceimpl_confirmarrival", "relation": "method", "confidence": "EXTRACTED", "source_file": "homestay-backend\\src\\main\\java\\com\\homestay3\\homestaybackend\\service\\impl\\CheckInServiceImpl.java", "source_location": "L218", "weight": 1.0}, {"source": "checkinserviceimpl_checkinserviceimpl", "target": "checkinserviceimpl_checkinserviceimpl_cancelpreparation", "relation": "method", "confidence": "EXTRACTED", "source_file": "homestay-backend\\src\\main\\java\\com\\homestay3\\homestaybackend\\service\\impl\\CheckInServiceImpl.java", "source_location": "L249", "weight": 1.0}, {"source": "checkinserviceimpl_checkinserviceimpl", "target": "checkinserviceimpl_checkinserviceimpl_getcheckinrecord", "relation": "method", "confidence": "EXTRACTED", "source_file": "homestay-backend\\src\\main\\java\\com\\homestay3\\homestaybackend\\service\\impl\\CheckInServiceImpl.java", "source_location": "L282", "weight": 1.0}, {"source": "checkinserviceimpl_checkinserviceimpl", "target": "checkinserviceimpl_checkinserviceimpl_validatecheckincode", "relation": "method", "confidence": "EXTRACTED", "source_file": "homestay-backend\\src\\main\\java\\com\\homestay3\\homestaybackend\\service\\impl\\CheckInServiceImpl.java", "source_location": "L293", "weight": 1.0}, {"source": "checkinserviceimpl_checkinserviceimpl", "target": "checkinserviceimpl_checkinserviceimpl_validateaccess", "relation": "method", "confidence": "EXTRACTED", "source_file": "homestay-backend\\src\\main\\java\\com\\homestay3\\homestaybackend\\service\\impl\\CheckInServiceImpl.java", "source_location": "L303", "weight": 1.0}, {"source": "checkinserviceimpl_checkinserviceimpl", "target": "checkinserviceimpl_checkinserviceimpl_getcurrentuser", "relation": "method", "confidence": "EXTRACTED", "source_file": "homestay-backend\\src\\main\\java\\com\\homestay3\\homestaybackend\\service\\impl\\CheckInServiceImpl.java", "source_location": "L316", "weight": 1.0}, {"source": "checkinserviceimpl_checkinserviceimpl", "target": "checkinserviceimpl_checkinserviceimpl_isorderowner", "relation": "method", "confidence": "EXTRACTED", "source_file": "homestay-backend\\src\\main\\java\\com\\homestay3\\homestaybackend\\service\\impl\\CheckInServiceImpl.java", "source_location": "L323", "weight": 1.0}, {"source": "checkinserviceimpl_checkinserviceimpl", "target": "checkinserviceimpl_checkinserviceimpl_isorderguest", "relation": "method", "confidence": "EXTRACTED", "source_file": "homestay-backend\\src\\main\\java\\com\\homestay3\\homestaybackend\\service\\impl\\CheckInServiceImpl.java", "source_location": "L328", "weight": 1.0}, {"source": "checkinserviceimpl_checkinserviceimpl", "target": "checkinserviceimpl_checkinserviceimpl_hasadminauthority", "relation": "method", "confidence": "EXTRACTED", "source_file": "homestay-backend\\src\\main\\java\\com\\homestay3\\homestaybackend\\service\\impl\\CheckInServiceImpl.java", "source_location": "L332", "weight": 1.0}, {"source": "checkinserviceimpl_checkinserviceimpl", "target": "checkinserviceimpl_checkinserviceimpl_isorderaccessible", "relation": "method", "confidence": "EXTRACTED", "source_file": "homestay-backend\\src\\main\\java\\com\\homestay3\\homestaybackend\\service\\impl\\CheckInServiceImpl.java", "source_location": "L336", "weight": 1.0}, {"source": "checkinserviceimpl_checkinserviceimpl", "target": "checkinserviceimpl_checkinserviceimpl_generatecheckincode", "relation": "method", "confidence": "EXTRACTED", "source_file": "homestay-backend\\src\\main\\java\\com\\homestay3\\homestaybackend\\service\\impl\\CheckInServiceImpl.java", "source_location": "L340", "weight": 1.0}, {"source": "checkinserviceimpl_checkinserviceimpl", "target": "checkinserviceimpl_checkinserviceimpl_parseautocheckintime", "relation": "method", "confidence": "EXTRACTED", "source_file": "homestay-backend\\src\\main\\java\\com\\homestay3\\homestaybackend\\service\\impl\\CheckInServiceImpl.java", "source_location": "L345", "weight": 1.0}, {"source": "checkinserviceimpl_checkinserviceimpl", "target": "checkinserviceimpl_checkinserviceimpl_converttodto", "relation": "method", "confidence": "EXTRACTED", "source_file": "homestay-backend\\src\\main\\java\\com\\homestay3\\homestaybackend\\service\\impl\\CheckInServiceImpl.java", "source_location": "L353", "weight": 1.0}, {"source": "checkinserviceimpl_checkinserviceimpl", "target": "checkinserviceimpl_checkinserviceimpl_sendcheckincredentialnotification", "relation": "method", "confidence": "EXTRACTED", "source_file": "homestay-backend\\src\\main\\java\\com\\homestay3\\homestaybackend\\service\\impl\\CheckInServiceImpl.java", "source_location": "L373", "weight": 1.0}, {"source": "checkinserviceimpl_checkinserviceimpl", "target": "checkinserviceimpl_checkinserviceimpl_sendcheckinconfirmationnotification", "relation": "method", "confidence": "EXTRACTED", "source_file": "homestay-backend\\src\\main\\java\\com\\homestay3\\homestaybackend\\service\\impl\\CheckInServiceImpl.java", "source_location": "L395", "weight": 1.0}, {"source": "checkinserviceimpl_checkinserviceimpl_preparecheckin", "target": "checkinserviceimpl_checkinserviceimpl_getcurrentuser", "relation": "calls", "confidence": "INFERRED", "source_file": "homestay-backend\\src\\main\\java\\com\\homestay3\\homestaybackend\\service\\impl\\CheckInServiceImpl.java", "source_location": "L59", "weight": 0.8}, {"source": "checkinserviceimpl_checkinserviceimpl_preparecheckin", "target": "checkinserviceimpl_checkinserviceimpl_isorderowner", "relation": "calls", "confidence": "INFERRED", "source_file": "homestay-backend\\src\\main\\java\\com\\homestay3\\homestaybackend\\service\\impl\\CheckInServiceImpl.java", "source_location": "L64", "weight": 0.8}, {"source": "checkinserviceimpl_checkinserviceimpl_preparecheckin", "target": "checkinserviceimpl_checkinserviceimpl_generatecheckincode", "relation": "calls", "confidence": "INFERRED", "source_file": "homestay-backend\\src\\main\\java\\com\\homestay3\\homestaybackend\\service\\impl\\CheckInServiceImpl.java", "source_location": "L74", "weight": 0.8}, {"source": "checkinserviceimpl_checkinserviceimpl_preparecheckin", "target": "checkinserviceimpl_checkinserviceimpl_parseautocheckintime", "relation": "calls", "confidence": "INFERRED", "source_file": "homestay-backend\\src\\main\\java\\com\\homestay3\\homestaybackend\\service\\impl\\CheckInServiceImpl.java", "source_location": "L77", "weight": 0.8}, {"source": "checkinserviceimpl_checkinserviceimpl_preparecheckin", "target": "checkinserviceimpl_checkinserviceimpl_sendcheckincredentialnotification", "relation": "calls", "confidence": "INFERRED", "source_file": "homestay-backend\\src\\main\\java\\com\\homestay3\\homestaybackend\\service\\impl\\CheckInServiceImpl.java", "source_location": "L105", "weight": 0.8}, {"source": "checkinserviceimpl_checkinserviceimpl_preparecheckin", "target": "checkinserviceimpl_checkinserviceimpl_converttodto", "relation": "calls", "confidence": "INFERRED", "source_file": "homestay-backend\\src\\main\\java\\com\\homestay3\\homestaybackend\\service\\impl\\CheckInServiceImpl.java", "source_location": "L108", "weight": 0.8}, {"source": "checkinserviceimpl_checkinserviceimpl_performcheckin", "target": "checkinserviceimpl_checkinserviceimpl_getcurrentuser", "relation": "calls", "confidence": "INFERRED", "source_file": "homestay-backend\\src\\main\\java\\com\\homestay3\\homestaybackend\\service\\impl\\CheckInServiceImpl.java", "source_location": "L136", "weight": 0.8}, {"source": "checkinserviceimpl_checkinserviceimpl_performcheckin", "target": "checkinserviceimpl_checkinserviceimpl_isorderowner", "relation": "calls", "confidence": "INFERRED", "source_file": "homestay-backend\\src\\main\\java\\com\\homestay3\\homestaybackend\\service\\impl\\CheckInServiceImpl.java", "source_location": "L141", "weight": 0.8}, {"source": "checkinserviceimpl_checkinserviceimpl_performcheckin", "target": "checkinserviceimpl_checkinserviceimpl_hasadminauthority", "relation": "calls", "confidence": "INFERRED", "source_file": "homestay-backend\\src\\main\\java\\com\\homestay3\\homestaybackend\\service\\impl\\CheckInServiceImpl.java", "source_location": "L141", "weight": 0.8}, {"source": "checkinserviceimpl_checkinserviceimpl_performcheckin", "target": "checkinserviceimpl_checkinserviceimpl_sendcheckinconfirmationnotification", "relation": "calls", "confidence": "INFERRED", "source_file": "homestay-backend\\src\\main\\java\\com\\homestay3\\homestaybackend\\service\\impl\\CheckInServiceImpl.java", "source_location": "L167", "weight": 0.8}, {"source": "checkinserviceimpl_checkinserviceimpl_performcheckin", "target": "checkinserviceimpl_checkinserviceimpl_converttodto", "relation": "calls", "confidence": "INFERRED", "source_file": "homestay-backend\\src\\main\\java\\com\\homestay3\\homestaybackend\\service\\impl\\CheckInServiceImpl.java", "source_location": "L170", "weight": 0.8}, {"source": "checkinserviceimpl_checkinserviceimpl_selfcheckin", "target": "checkinserviceimpl_checkinserviceimpl_sendcheckinconfirmationnotification", "relation": "calls", "confidence": "INFERRED", "source_file": "homestay-backend\\src\\main\\java\\com\\homestay3\\homestaybackend\\service\\impl\\CheckInServiceImpl.java", "source_location": "L212", "weight": 0.8}, {"source": "checkinserviceimpl_checkinserviceimpl_selfcheckin", "target": "checkinserviceimpl_checkinserviceimpl_converttodto", "relation": "calls", "confidence": "INFERRED", "source_file": "homestay-backend\\src\\main\\java\\com\\homestay3\\homestaybackend\\service\\impl\\CheckInServiceImpl.java", "source_location": "L215", "weight": 0.8}, {"source": "checkinserviceimpl_checkinserviceimpl_confirmarrival", "target": "checkinserviceimpl_checkinserviceimpl_getcurrentuser", "relation": "calls", "confidence": "INFERRED", "source_file": "homestay-backend\\src\\main\\java\\com\\homestay3\\homestaybackend\\service\\impl\\CheckInServiceImpl.java", "source_location": "L220", "weight": 0.8}, {"source": "checkinserviceimpl_checkinserviceimpl_confirmarrival", "target": "checkinserviceimpl_checkinserviceimpl_isorderguest", "relation": "calls", "confidence": "INFERRED", "source_file": "homestay-backend\\src\\main\\java\\com\\homestay3\\homestaybackend\\service\\impl\\CheckInServiceImpl.java", "source_location": "L225", "weight": 0.8}, {"source": "checkinserviceimpl_checkinserviceimpl_confirmarrival", "target": "checkinserviceimpl_checkinserviceimpl_converttodto", "relation": "calls", "confidence": "INFERRED", "source_file": "homestay-backend\\src\\main\\java\\com\\homestay3\\homestaybackend\\service\\impl\\CheckInServiceImpl.java", "source_location": "L246", "weight": 0.8}, {"source": "checkinserviceimpl_checkinserviceimpl_cancelpreparation", "target": "checkinserviceimpl_checkinserviceimpl_getcurrentuser", "relation": "calls", "confidence": "INFERRED", "source_file": "homestay-backend\\src\\main\\java\\com\\homestay3\\homestaybackend\\service\\impl\\CheckInServiceImpl.java", "source_location": "L252", "weight": 0.8}, {"source": "checkinserviceimpl_checkinserviceimpl_cancelpreparation", "target": "checkinserviceimpl_checkinserviceimpl_isorderowner", "relation": "calls", "confidence": "INFERRED", "source_file": "homestay-backend\\src\\main\\java\\com\\homestay3\\homestaybackend\\service\\impl\\CheckInServiceImpl.java", "source_location": "L257", "weight": 0.8}, {"source": "checkinserviceimpl_checkinserviceimpl_cancelpreparation", "target": "checkinserviceimpl_checkinserviceimpl_converttodto", "relation": "calls", "confidence": "INFERRED", "source_file": "homestay-backend\\src\\main\\java\\com\\homestay3\\homestaybackend\\service\\impl\\CheckInServiceImpl.java", "source_location": "L279", "weight": 0.8}, {"source": "checkinserviceimpl_checkinserviceimpl_getcheckinrecord", "target": "checkinserviceimpl_checkinserviceimpl_converttodto", "relation": "calls", "confidence": "INFERRED", "source_file": "homestay-backend\\src\\main\\java\\com\\homestay3\\homestaybackend\\service\\impl\\CheckInServiceImpl.java", "source_location": "L290", "weight": 0.8}, {"source": "checkinserviceimpl_checkinserviceimpl_validateaccess", "target": "checkinserviceimpl_checkinserviceimpl_isorderaccessible", "relation": "calls", "confidence": "INFERRED", "source_file": "homestay-backend\\src\\main\\java\\com\\homestay3\\homestaybackend\\service\\impl\\CheckInServiceImpl.java", "source_location": "L309", "weight": 0.8}, {"source": "checkinserviceimpl_checkinserviceimpl_isorderaccessible", "target": "checkinserviceimpl_checkinserviceimpl_isorderowner", "relation": "calls", "confidence": "INFERRED", "source_file": "homestay-backend\\src\\main\\java\\com\\homestay3\\homestaybackend\\service\\impl\\CheckInServiceImpl.java", "source_location": "L337", "weight": 0.8}, {"source": "checkinserviceimpl_checkinserviceimpl_isorderaccessible", "target": "checkinserviceimpl_checkinserviceimpl_isorderguest", "relation": "calls", "confidence": "INFERRED", "source_file": "homestay-backend\\src\\main\\java\\com\\homestay3\\homestaybackend\\service\\impl\\CheckInServiceImpl.java", "source_location": "L337", "weight": 0.8}, {"source": "checkinserviceimpl_checkinserviceimpl_isorderaccessible", "target": "checkinserviceimpl_checkinserviceimpl_hasadminauthority", "relation": "calls", "confidence": "INFERRED", "source_file": "homestay-backend\\src\\main\\java\\com\\homestay3\\homestaybackend\\service\\impl\\CheckInServiceImpl.java", "source_location": "L337", "weight": 0.8}]}